textual_mandelbrot/__init__.py
textual_mandelbrot/__main__.py
textual_mandelbrot/colouring.py
textual_mandelbrot/commands.py
textual_mandelbrot/mandelbrot.py
textual_mandelbrot-0.8.2.dist-info/METADATA
textual_mandelbrot-0.8.2.dist-info/WHEEL
textual_mandelbrot-0.8.2.dist-info/entry_points.txt
textual_mandelbrot-0.8.2.dist-info/licenses/LICENSE
textual_mandelbrot-0.8.2.dist-info/RECORD
