Metadata-Version: 2.3
Name: textual-mandelbrot
Version: 0.8.2
Summary: A simple Mandelbrot explorer for the terminal
Project-URL: Homepage, https://github.com/davep/textual-mandelbrot
Project-URL: Repository, https://github.com/davep/textual-mandelbrot
Project-URL: Documentation, https://github.com/davep/textual-mandelbrot
Project-URL: Source, https://github.com/davep/textual-mandelbrot
Project-URL: Issues, https://github.com/davep/textual-mandelbrot/issues
Project-URL: Discussions, https://github.com/davep/textual-mandelbrot/discussions
Author-email: Dave Pearson <davep@davep.org>
License: MIT License
Keywords: library,mandelbrot,maths,terminal
Classifier: Development Status :: 3 - Alpha
Classifier: Environment :: Console
Classifier: Intended Audience :: Developers
Classifier: License :: OSI Approved :: MIT License
Classifier: Operating System :: OS Independent
Classifier: Programming Language :: Python :: 3.10
Classifier: Programming Language :: Python :: 3.11
Classifier: Programming Language :: Python :: 3.12
Classifier: Programming Language :: Python :: 3.13
Classifier: Topic :: Software Development :: Libraries
Classifier: Topic :: Terminals
Classifier: Typing :: Typed
Requires-Python: >=3.10
Requires-Dist: textual-canvas>=0.2.1
Requires-Dist: textual>=3.1.0
